natrix/__init__.py
natrix/__main__.py
natrix/__version__.py
natrix/ast_node.py
natrix/ast_tools.py
natrix/codegen.py
natrix/py.typed
natrix/rules/arg_naming_convention.py
natrix/rules/common.py
natrix/rules/constants_naming.py
natrix/rules/implicit_export.py
natrix/rules/implicit_internal.py
natrix/rules/implicit_pure.py
natrix/rules/implicit_view.py
natrix/rules/memory_expansion.py
natrix/rules/modifiers_ordering.py
natrix/rules/print_left.py
natrix/rules/storage_caching.py
natrix/rules/unused_arg.py
natrix/rules/unused_variable.py
natrix-0.1.9.dist-info/METADATA
natrix-0.1.9.dist-info/WHEEL
natrix-0.1.9.dist-info/entry_points.txt
natrix-0.1.9.dist-info/licenses/LICENSE
natrix-0.1.9.dist-info/RECORD
