Metadata-Version: 2.4
Name: natrix
Version: 0.1.9
Summary: A Vyper linter for fine sneks.
Author-email: Alberto Centonze <albicento.ac@gmail.com>
License-File: LICENSE
Requires-Python: >=3.10
Requires-Dist: tomli>=2.0.0; python_version < '3.11'
